{
    "asset": {
        "version": "0.0"
    },
    "geometricError": 4.0,
    "root": {
        "boundingVolume": {
            "sphere": [
                968.82378462,
                488.409353846,
                53.6588799804,
                16.253932822400225
            ]
        },
        "refine": "replace",
        "geometricError": 2.0,
        "content": {
            "url": "tile_4_4_16_tex.b3dm"
        },
        "children": [
            {
                "boundingVolume": {
                    "sphere": [
                        964.9175346155,
                        484.5031038461,
                        48.99562099645,
                        8.199447427912667
                    ]
                },
                "geometricError": 1.0,
                "content": {
                    "url": "tile_5_4_16_tex.b3dm"
                }
            },
            {
                "boundingVolume": {
                    "sphere": [
                        964.9175346155,
                        492.3156038461,
                        53.8223692781,
                        12.991007693371904
                    ]
                },
                "geometricError": 1.0,
                "content": {
                    "url": "tile_5_4_17_tex.b3dm"
                }
            },
            {
                "boundingVolume": {
                    "sphere": [
                        972.73003461545,
                        484.5031038461,
                        48.684645208999999,
                        7.971345237598598
                    ]
                },
                "geometricError": 1.0,
                "content": {
                    "url": "tile_5_5_16_tex.b3dm"
                }
            },
            {
                "boundingVolume": {
                    "sphere": [
                        972.7300346155,
                        492.3156038461,
                        48.139633521,
                        8.447780953495953
                    ]
                },
                "geometricError": 1.0,
                "content": {
                    "url": "tile_5_5_17_tex.b3dm"
                }
            }
        ]
    }
}