{
    "asset": {
        "version": "0.0"
    },
    "geometricError": 4.0,
    "root": {
        "boundingVolume": {
            "sphere": [
                953.19878462,
                441.534353846,
                66.88330212860001,
                18.09185796450537
            ]
        },
        "refine": "replace",
        "geometricError": 2.0,
        "content": {
            "url": "tile_4_2_10_tex.b3dm"
        },
        "children": [
            {
                "boundingVolume": {
                    "sphere": [
                        949.2925346155,
                        437.62810384615,
                        66.98128168245,
                        15.247226473089896
                    ]
                },
                "geometricError": 1.0,
                "content": {
                    "url": "tile_5_2_10_tex.b3dm"
                }
            },
            {
                "boundingVolume": {
                    "sphere": [
                        949.2925346155,
                        445.4406038461,
                        62.863264271199998,
                        5.718899258980162
                    ]
                },
                "geometricError": 1.0,
                "content": {
                    "url": "tile_5_2_11_tex.b3dm"
                }
            },
            {
                "boundingVolume": {
                    "sphere": [
                        957.1050346155,
                        437.62810384615,
                        57.727817327,
                        7.291091108014468
                    ]
                },
                "geometricError": 1.0,
                "content": {
                    "url": "tile_5_3_10_tex.b3dm"
                }
            },
            {
                "boundingVolume": {
                    "sphere": [
                        957.1050346155,
                        445.4406038461,
                        57.729564038999999,
                        7.591075621181203
                    ]
                },
                "geometricError": 1.0,
                "content": {
                    "url": "tile_5_3_11_tex.b3dm"
                }
            }
        ]
    }
}