{
    "asset": {
        "version": "0.0"
    },
    "geometricError": 4.0,
    "root": {
        "boundingVolume": {
            "sphere": [
                1000.07378462,
                488.409353846,
                63.6398036026,
                22.82362420696226
            ]
        },
        "refine": "replace",
        "geometricError": 2.0,
        "content": {
            "url": "tile_4_8_16_tex.b3dm"
        },
        "children": [
            {
                "boundingVolume": {
                    "sphere": [
                        996.1675346155,
                        484.5031038461,
                        65.54251590999999,
                        18.894089853269507
                    ]
                },
                "geometricError": 1.0,
                "content": {
                    "url": "tile_5_8_16_tex.b3dm"
                }
            },
            {
                "boundingVolume": {
                    "sphere": [
                        996.1675346155,
                        492.3156038461,
                        62.1146686963,
                        19.239574321961979
                    ]
                },
                "geometricError": 1.0,
                "content": {
                    "url": "tile_5_8_17_tex.b3dm"
                }
            },
            {
                "boundingVolume": {
                    "sphere": [
                        1003.9800346155,
                        484.50310384615,
                        66.4353526096,
                        15.977565369813745
                    ]
                },
                "geometricError": 1.0,
                "content": {
                    "url": "tile_5_9_16_tex.b3dm"
                }
            },
            {
                "boundingVolume": {
                    "sphere": [
                        1003.9800346155,
                        492.3156038461,
                        57.221300195,
                        12.692895249923949
                    ]
                },
                "geometricError": 1.0,
                "content": {
                    "url": "tile_5_9_17_tex.b3dm"
                }
            }
        ]
    }
}