{
    "asset": {
        "version": "0.0"
    },
    "geometricError": 4.0,
    "root": {
        "boundingVolume": {
            "sphere": [
                1031.32378462,
                457.159353846,
                68.58586490005,
                12.777910145535645
            ]
        },
        "refine": "replace",
        "geometricError": 2.0,
        "content": {
            "url": "tile_4_12_12_tex.b3dm"
        },
        "children": [
            {
                "boundingVolume": {
                    "sphere": [
                        1027.4175346155,
                        453.25310384604998,
                        67.560382545,
                        7.489135268948724
                    ]
                },
                "geometricError": 1.0,
                "content": {
                    "url": "tile_5_12_12_tex.b3dm"
                }
            },
            {
                "boundingVolume": {
                    "sphere": [
                        1027.4175346155,
                        461.0656038461,
                        67.9739557034,
                        8.015041466954207
                    ]
                },
                "geometricError": 1.0,
                "content": {
                    "url": "tile_5_12_13_tex.b3dm"
                }
            },
            {
                "boundingVolume": {
                    "sphere": [
                        1035.2300346155,
                        453.2531038461,
                        67.52966127650001,
                        7.428986260749039
                    ]
                },
                "geometricError": 1.0,
                "content": {
                    "url": "tile_5_13_12_tex.b3dm"
                }
            },
            {
                "boundingVolume": {
                    "sphere": [
                        1035.2300346155,
                        461.0656038461,
                        72.5700258196,
                        6.037835628901511
                    ]
                },
                "geometricError": 1.0,
                "content": {
                    "url": "tile_5_13_13_tex.b3dm"
                }
            }
        ]
    }
}