{
    "asset": {
        "version": "0.0"
    },
    "geometricError": 4.0,
    "root": {
        "boundingVolume": {
            "sphere": [
                1140.69878462,
                394.659353846,
                61.13516682645,
                11.166104185198986
            ]
        },
        "refine": "replace",
        "geometricError": 2.0,
        "content": {
            "url": "tile_4_26_4_tex.b3dm"
        },
        "children": [
            {
                "boundingVolume": {
                    "sphere": [
                        1136.7925346155,
                        390.7531038461,
                        60.8572657305,
                        5.593384947417978
                    ]
                },
                "geometricError": 1.0,
                "content": {
                    "url": "tile_5_26_4_tex.b3dm"
                }
            },
            {
                "boundingVolume": {
                    "sphere": [
                        1136.7925346155,
                        398.5656038461,
                        60.8065348995,
                        5.63782025666754
                    ]
                },
                "geometricError": 1.0,
                "content": {
                    "url": "tile_5_26_5_tex.b3dm"
                }
            },
            {
                "boundingVolume": {
                    "sphere": [
                        1144.6050346155,
                        390.7531038461,
                        61.1456444039,
                        5.752859619949171
                    ]
                },
                "geometricError": 1.0,
                "content": {
                    "url": "tile_5_27_4_tex.b3dm"
                }
            },
            {
                "boundingVolume": {
                    "sphere": [
                        1144.6050346155,
                        398.5656038461,
                        61.11478153255,
                        5.655030887519923
                    ]
                },
                "geometricError": 1.0,
                "content": {
                    "url": "tile_5_27_5_tex.b3dm"
                }
            }
        ]
    }
}