{
    "asset": {
        "version": "0.0"
    },
    "geometricError": 4.0,
    "root": {
        "boundingVolume": {
            "sphere": [
                953.19878462,
                379.034353846,
                90.08409523245001,
                13.330563607828959
            ]
        },
        "refine": "replace",
        "geometricError": 2.0,
        "content": {
            "url": "tile_4_2_2_tex.b3dm"
        },
        "children": [
            {
                "boundingVolume": {
                    "sphere": [
                        949.2925346155,
                        375.1281038461,
                        90.09224700050001,
                        9.28981044085194
                    ]
                },
                "geometricError": 1.0,
                "content": {
                    "url": "tile_5_2_2_tex.b3dm"
                }
            },
            {
                "boundingVolume": {
                    "sphere": [
                        949.2925346155,
                        382.9406038461,
                        89.6040071995,
                        8.882054796637578
                    ]
                },
                "geometricError": 1.0,
                "content": {
                    "url": "tile_5_2_3_tex.b3dm"
                }
            },
            {
                "boundingVolume": {
                    "sphere": [
                        957.1050346155,
                        375.1281038461,
                        93.6821726111,
                        6.694369750782054
                    ]
                },
                "geometricError": 1.0,
                "content": {
                    "url": "tile_5_3_2_tex.b3dm"
                }
            },
            {
                "boundingVolume": {
                    "sphere": [
                        957.1050346155,
                        382.9406038461,
                        91.47782775735,
                        7.537806872350463
                    ]
                },
                "geometricError": 1.0,
                "content": {
                    "url": "tile_5_3_3_tex.b3dm"
                }
            }
        ]
    }
}