{
    "asset": {
        "version": "0.0"
    },
    "geometricError": 4.0,
    "root": {
        "boundingVolume": {
            "sphere": [
                1000.07378462,
                597.784353846,
                68.91419790489999,
                38.009420755051248
            ]
        },
        "refine": "replace",
        "geometricError": 2.0,
        "content": {
            "url": "tile_4_8_30_tex.b3dm"
        },
        "children": [
            {
                "boundingVolume": {
                    "sphere": [
                        996.1675346155,
                        593.8781038461,
                        75.1684056709,
                        30.554984612020545
                    ]
                },
                "geometricError": 1.0,
                "content": {
                    "url": "tile_5_8_30_tex.b3dm"
                }
            },
            {
                "boundingVolume": {
                    "sphere": [
                        996.1675346155,
                        601.6906038461,
                        44.93304817735,
                        13.666712701809378
                    ]
                },
                "geometricError": 1.0,
                "content": {
                    "url": "tile_5_8_31_tex.b3dm"
                }
            },
            {
                "boundingVolume": {
                    "sphere": [
                        1003.9800346155,
                        593.8781038461,
                        75.06546798045,
                        30.717751404782577
                    ]
                },
                "geometricError": 1.0,
                "content": {
                    "url": "tile_5_9_30_tex.b3dm"
                }
            },
            {
                "boundingVolume": {
                    "sphere": [
                        1003.9800346155,
                        601.6906038461,
                        73.11580245385,
                        28.805432761217348
                    ]
                },
                "geometricError": 1.0,
                "content": {
                    "url": "tile_5_9_31_tex.b3dm"
                }
            }
        ]
    }
}