{
    "asset": {
        "version": "0.0"
    },
    "geometricError": 4.0,
    "root": {
        "boundingVolume": {
            "sphere": [
                984.4487846155,
                144.6593538461,
                97.0180517747,
                16.20801023265263
            ]
        },
        "refine": "replace",
        "geometricError": 2.0,
        "content": {
            "url": "tile_4_6_4_tex.b3dm"
        },
        "children": [
            {
                "boundingVolume": {
                    "sphere": [
                        980.5425346155,
                        140.7531038461,
                        93.39942313935,
                        8.94252150434584
                    ]
                },
                "geometricError": 1.0,
                "content": {
                    "url": "tile_5_6_4_tex.b3dm"
                }
            },
            {
                "boundingVolume": {
                    "sphere": [
                        980.5425346155,
                        148.5656038461,
                        97.5981181201,
                        12.56593037595504
                    ]
                },
                "geometricError": 1.0,
                "content": {
                    "url": "tile_5_6_5_tex.b3dm"
                }
            },
            {
                "boundingVolume": {
                    "sphere": [
                        988.3550346155,
                        140.7531038461,
                        85.98524284909999,
                        5.590196498784249
                    ]
                },
                "geometricError": 1.0,
                "content": {
                    "url": "tile_5_7_4_tex.b3dm"
                }
            },
            {
                "boundingVolume": {
                    "sphere": [
                        988.3550346155,
                        148.5656038461,
                        94.69422588104999,
                        10.997080961375004
                    ]
                },
                "geometricError": 1.0,
                "content": {
                    "url": "tile_5_7_5_tex.b3dm"
                }
            }
        ]
    }
}