{
    "asset": {
        "version": "0.0"
    },
    "geometricError": 8.0,
    "root": {
        "boundingVolume": {
            "sphere": [
                945.3862846155,
                339.9718538461,
                102.5365524857,
                25.116576307255014
            ]
        },
        "refine": "replace",
        "geometricError": 4.0,
        "content": {
            "url": "tile_3_0_28_tex.b3dm"
        },
        "children": [
            {
                "boundingVolume": {
                    "sphere": [
                        937.5737846155,
                        332.1593538461,
                        106.91431530575,
                        12.321497971101353
                    ]
                },
                "geometricError": 2.0,
                "content": {
                    "url": "tile_4_0_28_tex.json"
                }
            },
            {
                "boundingVolume": {
                    "sphere": [
                        937.5737846155,
                        347.7843538461,
                        106.40763780115,
                        12.30069432658082
                    ]
                },
                "geometricError": 2.0,
                "content": {
                    "url": "tile_4_0_30_tex.json"
                }
            },
            {
                "boundingVolume": {
                    "sphere": [
                        953.1987846155,
                        332.1593538461,
                        110.69959323270001,
                        11.70750968772301
                    ]
                },
                "geometricError": 2.0,
                "content": {
                    "url": "tile_4_2_28_tex.json"
                }
            },
            {
                "boundingVolume": {
                    "sphere": [
                        953.1987846155,
                        347.7843538461,
                        101.13433574875,
                        15.345592501215135
                    ]
                },
                "geometricError": 2.0,
                "content": {
                    "url": "tile_4_2_30_tex.json"
                }
            }
        ]
    }
}