{
    "asset": {
        "version": "0.0"
    },
    "geometricError": 4.0,
    "root": {
        "boundingVolume": {
            "sphere": [
                937.5737846155,
                254.03435384609998,
                109.836552164,
                14.959811554543407
            ]
        },
        "refine": "replace",
        "geometricError": 2.0,
        "content": {
            "url": "tile_4_0_18_tex.b3dm"
        },
        "children": [
            {
                "boundingVolume": {
                    "sphere": [
                        933.6675346155,
                        250.1281038461,
                        116.74000370195,
                        6.3753934522543569
                    ]
                },
                "geometricError": 1.0,
                "content": {
                    "url": "tile_5_0_18_tex.b3dm"
                }
            },
            {
                "boundingVolume": {
                    "sphere": [
                        933.6675346155,
                        257.9406038461,
                        113.74007889744999,
                        7.266215300373699
                    ]
                },
                "geometricError": 1.0,
                "content": {
                    "url": "tile_5_0_19_tex.b3dm"
                }
            },
            {
                "boundingVolume": {
                    "sphere": [
                        941.4800346155,
                        250.1281038461,
                        108.00418717545,
                        9.408552737053192
                    ]
                },
                "geometricError": 1.0,
                "content": {
                    "url": "tile_5_1_18_tex.b3dm"
                }
            },
            {
                "boundingVolume": {
                    "sphere": [
                        941.4800346155,
                        257.9406038461,
                        109.095015956,
                        10.893880119385298
                    ]
                },
                "geometricError": 1.0,
                "content": {
                    "url": "tile_5_1_19_tex.b3dm"
                }
            }
        ]
    }
}